crazymemory/__init__.py
crazymemory/client.py
crazymemory/mcp_client.py
crazymemory-1.0.0.dist-info/METADATA
crazymemory-1.0.0.dist-info/WHEEL
crazymemory-1.0.0.dist-info/top_level.txt
crazymemory-1.0.0.dist-info/RECORD
