Metadata-Version: 2.4
Name: crazymemory
Version: 1.0.0
Summary: The AI Operating System - Connect all your AIs (ChatGPT, Claude, Gemini) to one universal memory
Author-email: DevMubarak <dev@neuralfabricx.com>
License: MIT
Project-URL: Homepage, https://github.com/devmubarak/crazymemory
Project-URL: Documentation, https://docs.neuralfabricx.com
Project-URL: Repository, https://github.com/devmubarak/crazymemory
Project-URL: Issues, https://github.com/devmubarak/crazymemory/issues
Keywords: ai,memory,context,mcp,llm,chatgpt,claude,fabric
Classifier: Development Status :: 4 - Beta
Classifier: Intended Audience :: Developers
Classifier: License :: OSI Approved :: MIT License
Classifier: Programming Language :: Python :: 3
Classifier: Programming Language :: Python :: 3.8
Classifier: Programming Language :: Python :: 3.9
Classifier: Programming Language :: Python :: 3.10
Classifier: Programming Language :: Python :: 3.11
Classifier: Programming Language :: Python :: 3.12
Classifier: Topic :: Software Development :: Libraries :: Python Modules
Classifier: Topic :: Scientific/Engineering :: Artificial Intelligence
Requires-Python: >=3.8
Requires-Dist: requests>=2.28.0
Requires-Dist: mcp>=1.0.0
Provides-Extra: dev
Requires-Dist: pytest>=7.0; extra == "dev"
Requires-Dist: black>=23.0; extra == "dev"
Requires-Dist: mypy>=1.0; extra == "dev"
Provides-Extra: mcp
Requires-Dist: mcp>=1.0.0; extra == "mcp"
Requires-Dist: anthropic>=0.40.0; extra == "mcp"
